setup.py
alibabacloud_ha3engine/__init__.py
alibabacloud_ha3engine/client.py
alibabacloud_ha3engine/models.py
alibabacloud_ha3engine.egg-info/PKG-INFO
alibabacloud_ha3engine.egg-info/SOURCES.txt
alibabacloud_ha3engine.egg-info/dependency_links.txt
alibabacloud_ha3engine.egg-info/requires.txt
alibabacloud_ha3engine.egg-info/top_level.txt